{"version": "0.1.8", "img_width": 1362, "img_height": 1920, "blocks": [{"box": [958, 285, 1158, 429], "vertical": false, "font_size": 80, "lines_coords": [[[958.0, 285.0], [1133.0, 285.0], [1133.0, 367.0], [958.0, 367.0]], [[958.0, 352.0], [1133.0, 352.0], [1133.0, 429.0], [958.0, 429.0]]], "lines": ["喧嘩を", "やめろ"]}, {"box": [846, 1635, 1138, 1841], "vertical": false, "font_size": 128, "lines_coords": [[[846.0, 1635.0], [1138.0, 1635.0], [1138.0, 1839.0], [846.0, 1839.0]], [[881.0, 1783.0], [1088.0, 1788.0], [1086.0, 1841.0], [879.0, 1835.0]]], "lines": ["彼らはもう立てない。やめたよ。", "やめたよ。"]}]}