{"version": "0.1.8", "img_width": 1362, "img_height": 1920, "blocks": [{"box": [151, 165, 1219, 391], "vertical": false, "font_size": 58, "lines_coords": [[[151.0, 175.0], [1219.0, 173.0], [1219.0, 241.0], [151.0, 243.0]], [[157.0, 251.0], [1119.0, 248.0], [1119.0, 308.0], [157.0, 312.0]], [[157.0, 325.0], [847.0, 326.0], [847.0, 387.0], [157.0, 385.0]]], "lines": ["Ｆｒｅｅｋａｒｉｌｉｒｅａｄｉｎｇ．．ｉｓｔｓｆｏｒｋｏｎｉｆｏｕｎｄ．．．", "ｉｎＣｒｙｓｔａｌｌＨｕｍｔａｒｓｃａｎｂｅｆｏｕｎｄａｔ：", "ｃｒｙｓｔａｌｉｎｔａｒｓｍａｎｇａｃｃｏｎ．"]}, {"box": [161, 754, 1226, 1102], "vertical": false, "font_size": 60, "lines_coords": [[[166.0, 756.0], [1183.0, 754.0], [1183.0, 816.0], [166.0, 818.0]], [[165.0, 823.0], [1181.0, 827.0], [1181.0, 895.0], [165.0, 891.0]], [[161.0, 896.0], [1226.0, 900.0], [1226.0, 972.0], [161.0, 968.0]], [[161.0, 973.0], [1138.0, 977.0], [1138.0, 1043.0], [161.0, 1040.0]], [[161.0, 1048.0], [343.0, 1052.0], [343.0, 1107.0], [161.0, 1103.0]]], "lines": ["Ｄｅｄｉｃａｔｅｄ＋ｏｍｙ．ｐａｒｅｎｔｓＫｅｒａｎｄ．ｃｒ．", "Ａｎｄｅｒｓｏｎ．ｃｏｍ．Ｔｈｏｎｋｙｏｕ．．．．それは、ｆｏｒｔｅａｃｈｉｎｇ．ｍｅ．", "．．．～～～．．．！！．．ｔｈｅ．ｊｏｙｏｆｒｅａｄｉｎｇ．エナ．．．．．．。エｔ＇ｓｂｅｃｕｓｅｅｃｏｆｙｏｕ．", "ｔｈａｔｌａｍａｂｌｅ．ｔｏｓｐｒｅｃｄｉｎｓｉｐｙｔｏ", "ｏｔｈｅｒｓ．"]}, {"box": [320, 1156, 761, 1203], "vertical": false, "font_size": 45, "lines_coords": [[[320.0, 1156.0], [761.0, 1158.0], [761.0, 1203.0], [320.0, 1201.0]]], "lines": ["～ＳｅａｎＡｎｄｅｒｓｏｎ"]}]}