{"version": "0.1.8", "img_width": 1070, "img_height": 1600, "blocks": [{"box": [82, 112, 194, 253], "vertical": true, "font_size": 32, "lines_coords": [[[153.0, 115.0], [185.0, 115.0], [185.0, 253.0], [153.0, 253.0]], [[118.0, 115.0], [146.0, 115.0], [146.0, 251.0], [118.0, 251.0]], [[82.0, 112.0], [117.0, 112.0], [117.0, 201.0], [82.0, 201.0]]], "lines": ["何か変じゃ", "ないですか", "あそこ"]}, {"box": [893, 553, 995, 695], "vertical": true, "font_size": 33, "lines_coords": [[[968.0, 557.0], [995.0, 557.0], [995.0, 695.0], [968.0, 695.0]], [[934.0, 556.0], [966.0, 556.0], [966.0, 660.0], [934.0, 660.0]], [[893.0, 553.0], [934.0, 553.0], [934.0, 614.0], [893.0, 614.0]]], "lines": ["おここだけ", "ごっそり", "無い"]}, {"box": [631, 554, 720, 650], "vertical": true, "font_size": 49, "lines_coords": [[[668.0, 554.0], [720.0, 559.0], [713.0, 626.0], [662.0, 621.0]], [[631.0, 557.0], [677.0, 556.0], [681.0, 648.0], [634.0, 650.0]]], "lines": ["これこれ", "痕跡か"]}, {"box": [171, 587, 268, 693], "vertical": true, "font_size": 33, "lines_coords": [[[234.0, 589.0], [268.0, 589.0], [268.0, 670.0], [234.0, 670.0]], [[203.0, 589.0], [235.0, 589.0], [235.0, 693.0], [203.0, 693.0]], [[171.0, 587.0], [204.0, 587.0], [204.0, 670.0], [171.0, 670.0]]], "lines": ["やっぱ", "そうです", "かね．．．"]}, {"box": [857, 960, 997, 1115], "vertical": true, "font_size": 32, "lines_coords": [[[959.0, 964.0], [991.0, 964.0], [991.0, 1092.0], [959.0, 1092.0]], [[924.0, 960.0], [963.0, 960.0], [963.0, 1048.0], [924.0, 1048.0]], [[893.0, 962.0], [921.0, 962.0], [918.0, 1115.0], [890.0, 1115.0]], [[857.0, 964.0], [884.0, 964.0], [884.0, 1090.0], [857.0, 1090.0]]], "lines": ["んー何だろ", "これ．．．", "何かの巣か．．．", "陣の跡か．．．"]}, {"box": [696, 1393, 841, 1501], "vertical": true, "font_size": 39, "lines_coords": [[[795.0, 1395.0], [840.0, 1395.0], [840.0, 1457.0], [795.0, 1457.0]], [[757.0, 1393.0], [804.0, 1395.0], [801.0, 1484.0], [754.0, 1482.0]], [[724.0, 1400.0], [760.0, 1400.0], [760.0, 1479.0], [724.0, 1479.0]], [[696.0, 1400.0], [724.0, 1400.0], [726.0, 1501.0], [698.0, 1501.0]]], "lines": ["他に", "無いか", "探して", "みましょ"]}, {"box": [140, 1328, 187, 1417], "vertical": true, "font_size": 47, "lines_coords": [[[140.0, 1328.0], [187.0, 1328.0], [187.0, 1417.0], [140.0, 1417.0]]], "lines": ["ん？"]}]}