{"version": "0.1.8", "img_width": 1070, "img_height": 1600, "blocks": [{"box": [506, 78, 539, 334], "vertical": true, "font_size": 32, "lines_coords": [[[506.0, 78.0], [538.0, 78.0], [538.0, 334.0], [506.0, 334.0]]], "lines": ["いいただきます．．．"]}, {"box": [122, 173, 159, 276], "vertical": true, "font_size": 37, "lines_coords": [[[122.0, 173.0], [159.0, 173.0], [159.0, 276.0], [122.0, 276.0]]], "lines": ["ハーイ"]}, {"box": [270, 548, 346, 687], "vertical": true, "font_size": 36, "lines_coords": [[[303.0, 548.0], [346.0, 548.0], [346.0, 615.0], [303.0, 615.0]], [[273.0, 551.0], [301.0, 551.0], [298.0, 687.0], [270.0, 687.0]]], "lines": ["もう", "泣きそう．．．"]}, {"box": [78, 540, 107, 673], "vertical": true, "font_size": 28, "lines_coords": [[[78.0, 540.0], [106.0, 540.0], [106.0, 671.0], [78.0, 671.0]]], "lines": ["うっそー"]}, {"box": [946, 1011, 1018, 1232], "vertical": true, "font_size": 27, "lines_coords": [[[980.0, 1014.0], [1007.0, 1014.0], [1007.0, 1232.0], [980.0, 1232.0]], [[946.0, 1012.0], [973.0, 1012.0], [973.0, 1178.0], [946.0, 1178.0]]], "lines": ["ウニって美味しく", "なくない～？"]}, {"box": [712, 1009, 774, 1229], "vertical": true, "font_size": 28, "lines_coords": [[[741.0, 1009.0], [774.0, 1009.0], [774.0, 1098.0], [741.0, 1098.0]], [[713.0, 1010.0], [735.0, 1010.0], [735.0, 1229.0], [713.0, 1229.0]]], "lines": ["みんな", "だまされてない？"]}, {"box": [584, 1011, 627, 1273], "vertical": true, "font_size": 33, "lines_coords": [[[584.0, 1012.0], [617.0, 1012.0], [620.0, 1273.0], [587.0, 1273.0]]], "lines": ["騙されてねーよ！"]}, {"box": [348, 814, 409, 926], "vertical": true, "font_size": 26, "lines_coords": [[[382.0, 815.0], [409.0, 815.0], [409.0, 926.0], [382.0, 926.0]], [[348.0, 814.0], [374.0, 814.0], [374.0, 926.0], [348.0, 926.0]]], "lines": ["うまっ！", "うまっ！"]}, {"box": [429, 1020, 537, 1206], "vertical": true, "font_size": 30, "lines_coords": [[[502.0, 1020.0], [537.0, 1020.0], [537.0, 1106.0], [502.0, 1106.0]], [[468.0, 1023.0], [495.0, 1023.0], [495.0, 1206.0], [468.0, 1206.0]], [[429.0, 1021.0], [456.0, 1021.0], [456.0, 1179.0], [429.0, 1179.0]]], "lines": ["あれだ", "回転寿司のとは", "全然ちがうぞ"]}, {"box": [371, 994, 390, 1073], "vertical": true, "font_size": 19, "lines_coords": [[[371.0, 994.0], [390.0, 994.0], [390.0, 1073.0], [371.0, 1073.0]]], "lines": ["こうかん"]}, {"box": [121, 1070, 154, 1173], "vertical": true, "font_size": 33, "lines_coords": [[[121.0, 1070.0], [154.0, 1070.0], [154.0, 1173.0], [121.0, 1173.0]]], "lines": ["んえー"]}, {"box": [410, 1229, 509, 1464], "vertical": true, "font_size": 30, "lines_coords": [[[474.0, 1229.0], [509.0, 1229.0], [509.0, 1293.0], [474.0, 1293.0]], [[448.0, 1235.0], [474.0, 1235.0], [474.0, 1464.0], [448.0, 1464.0]], [[410.0, 1235.0], [438.0, 1235.0], [438.0, 1339.0], [410.0, 1339.0]]], "lines": ["ほら", "ちょっとあげるから", "食べてみ"]}]}