{"version": "0.1.8", "img_width": 1070, "img_height": 1600, "blocks": [{"box": [826, 154, 944, 368], "vertical": true, "font_size": 24, "lines_coords": [[[920.0, 157.0], [941.0, 157.0], [941.0, 356.0], [920.0, 356.0]], [[887.0, 154.0], [913.0, 154.0], [913.0, 368.0], [887.0, 368.0]], [[852.0, 154.0], [879.0, 154.0], [879.0, 300.0], [852.0, 300.0]], [[826.0, 156.0], [848.0, 156.0], [848.0, 251.0], [826.0, 251.0]]], "lines": ["あじゃあオロルが", "そのフクロウくんの", "誤解を解いて", "あげてよ"]}, {"box": [534, 178, 579, 217], "vertical": false, "font_size": 39, "lines_coords": [[[534.0, 178.0], [579.0, 178.0], [579.0, 217.0], [534.0, 217.0]]], "lines": ["ホ"]}, {"box": [415, 164, 487, 357], "vertical": true, "font_size": 32, "lines_coords": [[[454.0, 165.0], [487.0, 165.0], [487.0, 276.0], [454.0, 276.0]], [[415.0, 164.0], [446.0, 164.0], [446.0, 357.0], [415.0, 357.0]]], "lines": ["オロルの", "知り合いなの？"]}, {"box": [78, 153, 108, 309], "vertical": true, "font_size": 28, "lines_coords": [[[78.0, 154.0], [106.0, 154.0], [106.0, 307.0], [78.0, 307.0]]], "lines": ["そうみたい"]}, {"box": [879, 509, 937, 696], "vertical": true, "font_size": 25, "lines_coords": [[[910.0, 509.0], [937.0, 509.0], [937.0, 696.0], [910.0, 696.0]], [[879.0, 509.0], [907.0, 509.0], [907.0, 609.0], [879.0, 609.0]]], "lines": ["オロル不動産業", "やってて"]}, {"box": [481, 501, 584, 740], "vertical": true, "font_size": 26, "lines_coords": [[[549.0, 503.0], [576.0, 503.0], [576.0, 740.0], [549.0, 740.0]], [[512.0, 501.0], [538.0, 501.0], [538.0, 703.0], [512.0, 703.0]], [[481.0, 501.0], [507.0, 501.0], [507.0, 653.0], [481.0, 653.0]]], "lines": ["ねすごい偶然だよね", "オロルと知り合い", "だったなんて"]}, {"box": [64, 621, 185, 737], "vertical": true, "font_size": 27, "lines_coords": [[[157.0, 621.0], [185.0, 621.0], [185.0, 726.0], [157.0, 726.0]], [[123.0, 621.0], [149.0, 621.0], [149.0, 735.0], [123.0, 735.0]], [[96.0, 621.0], [123.0, 621.0], [123.0, 715.0], [96.0, 715.0]], [[64.0, 621.0], [90.0, 621.0], [90.0, 737.0], [64.0, 737.0]]], "lines": ["あいや．．．", "不動産業の", "ところに", "驚いてます"]}, {"box": [849, 754, 943, 982], "vertical": true, "font_size": 25, "lines_coords": [[[916.0, 754.0], [943.0, 754.0], [941.0, 982.0], [915.0, 982.0]], [[882.0, 757.0], [904.0, 757.0], [904.0, 929.0], [882.0, 929.0]], [[849.0, 759.0], [871.0, 759.0], [871.0, 956.0], [849.0, 956.0]]], "lines": ["そのフクロウくんに", "巣箱紹介したの", "オロルなんだって"]}, {"box": [629, 904, 663, 1000], "vertical": true, "font_size": 34, "lines_coords": [[[629.0, 904.0], [663.0, 904.0], [663.0, 1000.0], [629.0, 1000.0]]], "lines": ["まじか"]}, {"box": [466, 829, 590, 1034], "vertical": true, "font_size": 25, "lines_coords": [[[563.0, 829.0], [590.0, 829.0], [590.0, 946.0], [563.0, 946.0]], [[529.0, 831.0], [556.0, 831.0], [556.0, 968.0], [529.0, 968.0]], [[496.0, 829.0], [520.0, 829.0], [521.0, 989.0], [498.0, 989.0]], [[467.0, 831.0], [488.0, 831.0], [488.0, 1034.0], [467.0, 1034.0]]], "lines": ["まこっさん", "オロルが彼に", "襲わないように", "説得してくれるって"]}, {"box": [64, 829, 155, 1022], "vertical": true, "font_size": 26, "lines_coords": [[[118.0, 829.0], [145.0, 829.0], [145.0, 975.0], [118.0, 975.0]], [[90.0, 831.0], [120.0, 831.0], [120.0, 906.0], [90.0, 906.0]], [[64.0, 831.0], [85.0, 831.0], [85.0, 1018.0], [64.0, 1018.0]]], "lines": ["本当ですか！？", "それは", "ありがたいです！！"]}, {"box": [845, 1178, 901, 1321], "vertical": true, "font_size": 56, "lines_coords": [[[845.0, 1178.0], [901.0, 1178.0], [901.0, 1321.0], [845.0, 1321.0]]], "lines": ["ホホー"]}, {"box": [494, 1129, 623, 1275], "vertical": true, "font_size": 28, "lines_coords": [[[588.0, 1129.0], [623.0, 1129.0], [623.0, 1209.0], [588.0, 1209.0]], [[557.0, 1131.0], [584.0, 1131.0], [584.0, 1253.0], [557.0, 1253.0]], [[523.0, 1131.0], [551.0, 1131.0], [548.0, 1251.0], [520.0, 1251.0]], [[495.0, 1135.0], [517.0, 1135.0], [517.0, 1275.0], [495.0, 1275.0]]], "lines": ["はい！", "じゃあ私も", "行った方が", "いいですよね"]}, {"box": [248, 1145, 342, 1292], "vertical": true, "font_size": 29, "lines_coords": [[[306.0, 1145.0], [338.0, 1146.0], [335.0, 1248.0], [303.0, 1246.0]], [[276.0, 1146.0], [310.0, 1146.0], [310.0, 1226.0], [276.0, 1226.0]], [[248.0, 1150.0], [270.0, 1150.0], [270.0, 1292.0], [248.0, 1292.0]]], "lines": ["食べたら", "すぐに", "行きましょう"]}, {"box": [178, 1346, 241, 1451], "vertical": true, "font_size": 31, "lines_coords": [[[212.0, 1346.0], [240.0, 1346.0], [240.0, 1451.0], [212.0, 1451.0]], [[178.0, 1346.0], [212.0, 1346.0], [212.0, 1428.0], [178.0, 1428.0]]], "lines": ["わたしも", "いこー"]}]}