{"version": "0.1.8", "img_width": 1070, "img_height": 1600, "blocks": [{"box": [449, 177, 484, 282], "vertical": true, "font_size": 35, "lines_coords": [[[449.0, 178.0], [484.0, 178.0], [484.0, 282.0], [449.0, 282.0]]], "lines": ["わっ！！"]}, {"box": [808, 903, 896, 1033], "vertical": true, "font_size": 28, "lines_coords": [[[863.0, 903.0], [896.0, 903.0], [896.0, 1007.0], [863.0, 1007.0]], [[837.0, 907.0], [865.0, 907.0], [865.0, 1009.0], [837.0, 1009.0]], [[809.0, 909.0], [831.0, 909.0], [831.0, 1032.0], [809.0, 1032.0]]], "lines": ["すごーい", "きれいに", "なったー！！"]}, {"box": [649, 1014, 706, 1109], "vertical": true, "font_size": 26, "lines_coords": [[[674.0, 1014.0], [706.0, 1014.0], [706.0, 1068.0], [674.0, 1068.0]], [[649.0, 1015.0], [676.0, 1015.0], [676.0, 1109.0], [649.0, 1109.0]]], "lines": ["はー", "なるほど"]}, {"box": [524, 1007, 609, 1165], "vertical": true, "font_size": 26, "lines_coords": [[[581.0, 1007.0], [609.0, 1007.0], [606.0, 1125.0], [577.0, 1125.0]], [[548.0, 1007.0], [570.0, 1007.0], [573.0, 1165.0], [551.0, 1165.0]], [[524.0, 1012.0], [542.0, 1012.0], [542.0, 1120.0], [524.0, 1120.0]]], "lines": ["建物自体に", "魔法がかかって", "たんですね"]}, {"box": [322, 896, 464, 1073], "vertical": true, "font_size": 24, "lines_coords": [[[426.0, 896.0], [452.0, 896.0], [452.0, 1023.0], [426.0, 1023.0]], [[390.0, 898.0], [417.0, 898.0], [417.0, 1025.0], [390.0, 1025.0]], [[356.0, 900.0], [378.0, 900.0], [378.0, 1048.0], [356.0, 1048.0]], [[324.0, 900.0], [345.0, 900.0], [345.0, 1073.0], [324.0, 1073.0]]], "lines": ["あの動きで", "本当の姿が", "見えるように", "してたんですよ"]}, {"box": [114, 940, 154, 1050], "vertical": true, "font_size": 40, "lines_coords": [[[114.0, 940.0], [154.0, 940.0], [154.0, 1050.0], [114.0, 1050.0]]], "lines": ["すげー"]}]}