{"version": "0.1.8", "img_width": 969, "img_height": 1381, "blocks": [{"box": [919, 20, 947, 233], "vertical": true, "font_size": 27, "lines_coords": [[[919.0, 20.0], [946.0, 20.0], [946.0, 233.0], [919.0, 233.0]]], "lines": ["あ、どうぞごうぞ"]}, {"box": [522, 33, 551, 171], "vertical": true, "font_size": 27, "lines_coords": [[[522.0, 33.0], [549.0, 33.0], [549.0, 171.0], [522.0, 171.0]]], "lines": ["いえどうぞ"]}, {"box": [386, 25, 449, 283], "vertical": true, "font_size": 26, "lines_coords": [[[424.0, 28.0], [448.0, 28.0], [448.0, 138.0], [424.0, 138.0]], [[386.0, 25.0], [413.0, 25.0], [416.0, 283.0], [389.0, 283.0]]], "lines": ["．．．じゃあ", "すみません貰います"]}, {"box": [24, 277, 61, 339], "vertical": true, "font_size": 37, "lines_coords": [[[24.0, 277.0], [61.0, 277.0], [61.0, 339.0], [24.0, 339.0]]], "lines": ["はい"]}, {"box": [504, 414, 563, 581], "vertical": true, "font_size": 28, "lines_coords": [[[530.0, 414.0], [563.0, 414.0], [563.0, 530.0], [530.0, 530.0]], [[504.0, 414.0], [526.0, 414.0], [526.0, 581.0], [504.0, 581.0]]], "lines": ["いえいえ", "どうでどうぞ"]}, {"box": [416, 383, 450, 472], "vertical": true, "font_size": 34, "lines_coords": [[[416.0, 383.0], [450.0, 383.0], [450.0, 472.0], [416.0, 472.0]]], "lines": ["あの．．．"]}, {"box": [888, 617, 950, 873], "vertical": true, "font_size": 28, "lines_coords": [[[921.0, 617.0], [950.0, 617.0], [947.0, 761.0], [919.0, 761.0]], [[888.0, 620.0], [915.0, 620.0], [915.0, 873.0], [888.0, 873.0]]], "lines": ["もし時間が", "あればなんですけど"]}, {"box": [793, 679, 855, 961], "vertical": true, "font_size": 28, "lines_coords": [[[827.0, 681.0], [855.0, 681.0], [855.0, 961.0], [827.0, 961.0]], [[793.0, 679.0], [820.0, 679.0], [820.0, 960.0], [793.0, 960.0]]], "lines": ["お礼にそこのカフェで", "１杯奢らせてください"]}, {"box": [25, 926, 56, 989], "vertical": true, "font_size": 31, "lines_coords": [[[25.0, 926.0], [56.0, 926.0], [56.0, 989.0], [25.0, 989.0]]], "lines": ["え？"]}, {"box": [858, 1093, 892, 1194], "vertical": true, "font_size": 34, "lines_coords": [[[858.0, 1093.0], [892.0, 1093.0], [892.0, 1194.0], [858.0, 1194.0]]], "lines": ["あ、はい"]}]}