{"version": "0.1.8", "img_width": 800, "img_height": 1146, "blocks": [{"box": [721, 69, 749, 207], "vertical": true, "font_size": 28, "lines_coords": [[[721.0, 69.0], [749.0, 69.0], [749.0, 205.0], [721.0, 205.0]]], "lines": ["うわぁー！！"]}, {"box": [311, 38, 335, 174], "vertical": true, "font_size": 23, "lines_coords": [[[311.0, 39.0], [334.0, 39.0], [334.0, 173.0], [311.0, 173.0]]], "lines": ["また負けた"]}, {"box": [30, 32, 93, 196], "vertical": true, "font_size": 31, "lines_coords": [[[62.0, 32.0], [93.0, 32.0], [93.0, 196.0], [62.0, 196.0]], [[30.0, 32.0], [61.0, 32.0], [61.0, 173.0], [30.0, 173.0]]], "lines": ["銃撃戦ゲーム", "難しいなー"]}, {"box": [702, 399, 764, 595], "vertical": true, "font_size": 30, "lines_coords": [[[732.0, 399.0], [764.0, 399.0], [761.0, 595.0], [730.0, 595.0]], [[702.0, 402.0], [730.0, 402.0], [730.0, 539.0], [702.0, 539.0]]], "lines": ["まぁしゃーない", "しゃーない"]}, {"box": [326, 386, 387, 551], "vertical": true, "font_size": 28, "lines_coords": [[[356.0, 386.0], [387.0, 386.0], [387.0, 551.0], [356.0, 551.0]], [[326.0, 387.0], [350.0, 387.0], [350.0, 494.0], [326.0, 494.0]]], "lines": ["運が悪かった", "だけだし"]}, {"box": [417, 755, 762, 865], "vertical": false, "font_size": 121, "lines_coords": [[[417.0, 744.0], [762.0, 744.0], [762.0, 876.0], [417.0, 876.0]]], "lines": ["はいはい．．．"]}]}