{"version": "0.1.8", "img_width": 1362, "img_height": 1920, "blocks": [{"box": [624, 1230, 874, 1402], "vertical": false, "font_size": 50, "lines_coords": [[[624.0, 1243.0], [853.0, 1230.0], [857.0, 1291.0], [628.0, 1305.0]], [[634.0, 1297.0], [795.0, 1301.0], [793.0, 1350.0], [632.0, 1346.0]], [[635.0, 1359.0], [874.0, 1359.0], [874.0, 1398.0], [635.0, 1398.0]]], "lines": ["こんにちは", "この水を", "使っていい？"]}, {"box": [102, 1749, 442, 1859], "vertical": false, "font_size": 48, "lines_coords": [[[105.0, 1749.0], [315.0, 1749.0], [315.0, 1801.0], [105.0, 1801.0]], [[106.0, 1811.0], [431.0, 1811.0], [431.0, 1856.0], [106.0, 1856.0]]], "lines": ["は．．．はい！", "この水を使って！"]}]}