{"version": "0.1.8", "img_width": 1300, "img_height": 1832, "blocks": [{"box": [923, 162, 949, 251], "vertical": true, "font_size": 26, "lines_coords": [[[923.0, 162.0], [949.0, 162.0], [949.0, 251.0], [923.0, 251.0]]], "lines": ["．．．．．．"]}, {"box": [275, 85, 404, 336], "vertical": true, "font_size": 41, "lines_coords": [[[359.0, 85.0], [404.0, 85.0], [404.0, 198.0], [359.0, 198.0]], [[316.0, 85.0], [359.0, 85.0], [359.0, 268.0], [316.0, 268.0]], [[275.0, 87.0], [311.0, 87.0], [311.0, 336.0], [275.0, 336.0]]], "lines": ["あれ？", "もしかして", "君はペンギン？"]}, {"box": [1032, 779, 1070, 994], "vertical": true, "font_size": 36, "lines_coords": [[[1033.0, 781.0], [1069.0, 781.0], [1069.0, 994.0], [1033.0, 994.0]]], "lines": ["そうだよね〜"]}, {"box": [96, 429, 180, 656], "vertical": true, "font_size": 37, "lines_coords": [[[139.0, 431.0], [177.0, 429.0], [180.0, 545.0], [143.0, 547.0]], [[96.0, 429.0], [132.0, 429.0], [132.0, 656.0], [96.0, 656.0]]], "lines": ["違うよ", "僕は人間だよ"]}, {"box": [625, 1223, 713, 1427], "vertical": true, "font_size": 42, "lines_coords": [[[672.0, 1225.0], [709.0, 1225.0], [713.0, 1427.0], [675.0, 1427.0]], [[625.0, 1223.0], [672.0, 1223.0], [672.0, 1340.0], [625.0, 1340.0]]], "lines": ["あ、ちょっと", "待って"]}, {"box": [255, 774, 341, 1068], "vertical": true, "font_size": 37, "lines_coords": [[[298.0, 774.0], [336.0, 774.0], [339.0, 1060.0], [302.0, 1060.0]], [[255.0, 776.0], [291.0, 776.0], [291.0, 1023.0], [255.0, 1023.0]]], "lines": ["くちばしがないし、", "翼もへんな形！"]}, {"box": [962, 1198, 1094, 1607], "vertical": true, "font_size": 40, "lines_coords": [[[1046.0, 1198.0], [1094.0, 1198.0], [1094.0, 1282.0], [1046.0, 1282.0]], [[1004.0, 1202.0], [1040.0, 1202.0], [1040.0, 1604.0], [1004.0, 1604.0]], [[962.0, 1204.0], [997.0, 1204.0], [997.0, 1386.0], [962.0, 1386.0]]], "lines": ["あ！", "ぼく急いでるんだった！！", "じゃあね！"]}, {"box": [230, 1288, 266, 1545], "vertical": true, "font_size": 31, "lines_coords": [[[230.0, 1288.0], [261.0, 1288.0], [261.0, 1545.0], [230.0, 1545.0]]], "lines": ["どこに行くの？"]}]}