{"version": "0.1.8", "img_width": 1070, "img_height": 1600, "blocks": [{"box": [959, 128, 991, 282], "vertical": true, "font_size": 29, "lines_coords": [[[959.0, 128.0], [991.0, 128.0], [991.0, 282.0], [959.0, 282.0]]], "lines": ["え～意外～"]}, {"box": [851, 104, 913, 326], "vertical": true, "font_size": 29, "lines_coords": [[[885.0, 107.0], [913.0, 107.0], [913.0, 218.0], [885.0, 218.0]], [[851.0, 104.0], [877.0, 104.0], [879.0, 326.0], [852.0, 326.0]]], "lines": ["見かけに", "よらないなぁ．．．"]}, {"box": [648, 107, 693, 153], "vertical": true, "font_size": 45, "lines_coords": [[[648.0, 107.0], [693.0, 107.0], [693.0, 153.0], [648.0, 153.0]]], "lines": ["ね"]}, {"box": [954, 673, 1001, 787], "vertical": true, "font_size": 39, "lines_coords": [[[954.0, 673.0], [993.0, 673.0], [993.0, 787.0], [954.0, 787.0]]], "lines": ["ん電話"]}, {"box": [385, 642, 462, 785], "vertical": true, "font_size": 33, "lines_coords": [[[424.0, 642.0], [462.0, 642.0], [462.0, 679.0], [424.0, 679.0]], [[385.0, 667.0], [413.0, 667.0], [413.0, 785.0], [385.0, 785.0]]], "lines": ["あ", "はいはい"]}, {"box": [977, 1061, 1004, 1209], "vertical": true, "font_size": 27, "lines_coords": [[[977.0, 1062.0], [1004.0, 1062.0], [1004.0, 1209.0], [977.0, 1209.0]]], "lines": ["アキラさん"]}, {"box": [796, 1048, 862, 1187], "vertical": true, "font_size": 28, "lines_coords": [[[832.0, 1048.0], [860.0, 1048.0], [862.0, 1160.0], [834.0, 1160.0]], [[799.0, 1048.0], [826.0, 1048.0], [823.0, 1187.0], [796.0, 1187.0]]], "lines": ["ちょっと", "すみません"]}, {"box": [685, 1073, 757, 1212], "vertical": true, "font_size": 32, "lines_coords": [[[720.0, 1073.0], [757.0, 1073.0], [757.0, 1134.0], [720.0, 1134.0]], [[685.0, 1076.0], [712.0, 1076.0], [712.0, 1212.0], [685.0, 1212.0]]], "lines": ["おー", "アキラさん"]}, {"box": [517, 1057, 629, 1271], "vertical": true, "font_size": 34, "lines_coords": [[[596.0, 1057.0], [629.0, 1057.0], [629.0, 1209.0], [596.0, 1209.0]], [[557.0, 1057.0], [595.0, 1057.0], [595.0, 1203.0], [557.0, 1203.0]], [[517.0, 1059.0], [549.0, 1059.0], [549.0, 1270.0], [517.0, 1270.0]]], "lines": ["もしもしー", "あはい～", "お疲れ様です〜"]}, {"box": [204, 1032, 309, 1228], "vertical": true, "font_size": 29, "lines_coords": [[[282.0, 1035.0], [309.0, 1035.0], [309.0, 1200.0], [282.0, 1200.0]], [[246.0, 1032.0], [274.0, 1032.0], [274.0, 1143.0], [246.0, 1143.0]], [[204.0, 1032.0], [235.0, 1032.0], [235.0, 1228.0], [204.0, 1228.0]]], "lines": ["アキラさんは", "えらくて", "かっこいい魔女"]}, {"box": [86, 1063, 125, 1292], "vertical": true, "font_size": 26, "lines_coords": [[[89.0, 1064.0], [115.0, 1064.0], [115.0, 1292.0], [89.0, 1292.0]]], "lines": ["魔女ばっかだなぁ"]}]}