{"version": "0.1.8", "img_width": 1070, "img_height": 1600, "blocks": [{"box": [876, 89, 979, 301], "vertical": true, "font_size": 29, "lines_coords": [[[951.0, 92.0], [977.0, 92.0], [977.0, 209.0], [951.0, 209.0]], [[913.0, 92.0], [945.0, 92.0], [945.0, 301.0], [913.0, 301.0]], [[877.0, 89.0], [905.0, 89.0], [904.0, 301.0], [876.0, 301.0]]], "lines": ["いきなり", "むずかしすぎや", "しませんか．．．？"]}, {"box": [471, 106, 592, 271], "vertical": true, "font_size": 34, "lines_coords": [[[559.0, 107.0], [592.0, 107.0], [592.0, 270.0], [559.0, 270.0]], [[509.0, 106.0], [546.0, 106.0], [546.0, 271.0], [509.0, 271.0]], [[471.0, 107.0], [502.0, 107.0], [502.0, 270.0], [471.0, 270.0]]], "lines": ["まぁそうね", "子守よりは", "はるかにね"]}, {"box": [201, 103, 240, 317], "vertical": true, "font_size": 33, "lines_coords": [[[201.0, 103.0], [234.0, 103.0], [237.0, 317.0], [204.0, 317.0]]], "lines": ["がんばれよ～"]}, {"box": [879, 631, 986, 887], "vertical": true, "font_size": 32, "lines_coords": [[[952.0, 631.0], [984.0, 631.0], [984.0, 843.0], [952.0, 843.0]], [[916.0, 632.0], [948.0, 632.0], [948.0, 887.0], [916.0, 887.0]], [[879.0, 631.0], [910.0, 631.0], [910.0, 814.0], [879.0, 814.0]]], "lines": ["え．．．あっはっ！？", "そそんないきなり", "そんな．．．っ！！"]}, {"box": [507, 617, 615, 790], "vertical": true, "font_size": 31, "lines_coords": [[[582.0, 617.0], [615.0, 617.0], [615.0, 735.0], [582.0, 735.0]], [[542.0, 618.0], [573.0, 618.0], [573.0, 790.0], [542.0, 790.0]], [[507.0, 618.0], [535.0, 618.0], [535.0, 760.0], [507.0, 760.0]]], "lines": ["まっまだ", "２つ目の仕事", "ですよっ！"]}, {"box": [879, 1079, 945, 1218], "vertical": true, "font_size": 28, "lines_coords": [[[916.0, 1079.0], [945.0, 1079.0], [941.0, 1218.0], [913.0, 1218.0]], [[882.0, 1079.0], [909.0, 1079.0], [905.0, 1218.0], [879.0, 1218.0]]], "lines": ["じょーだん", "じょーだん"]}, {"box": [465, 857, 598, 1004], "vertical": true, "font_size": 30, "lines_coords": [[[565.0, 860.0], [598.0, 862.0], [595.0, 960.0], [562.0, 959.0]], [[526.0, 857.0], [562.0, 857.0], [562.0, 937.0], [526.0, 937.0]], [[496.0, 860.0], [523.0, 860.0], [523.0, 1004.0], [496.0, 1004.0]], [[465.0, 860.0], [488.0, 860.0], [492.0, 1001.0], [468.0, 1001.0]]], "lines": ["ハハハ！！", "真琴の", "困った顔って", "かわいいなぁ"]}, {"box": [428, 1106, 477, 1264], "vertical": true, "font_size": 37, "lines_coords": [[[428.0, 1106.0], [465.0, 1106.0], [465.0, 1264.0], [428.0, 1264.0]]], "lines": ["あ相棒．．．"]}, {"box": [48, 823, 115, 937], "vertical": true, "font_size": 33, "lines_coords": [[[79.0, 823.0], [112.0, 823.0], [115.0, 937.0], [82.0, 937.0]], [[48.0, 823.0], [81.0, 823.0], [81.0, 910.0], [48.0, 910.0]]], "lines": ["かわっ．．．", "なっ！？"]}, {"box": [531, 1264, 613, 1525], "vertical": true, "font_size": 29, "lines_coords": [[[573.0, 1264.0], [604.0, 1264.0], [604.0, 1470.0], [573.0, 1470.0]], [[532.0, 1268.0], [559.0, 1268.0], [559.0, 1525.0], [532.0, 1525.0]]], "lines": ["ちゃんと相棒も", "いるから大丈夫だよ"]}]}