{"version": "0.1.8", "img_width": 1070, "img_height": 1600, "blocks": [{"box": [893, 507, 988, 701], "vertical": true, "font_size": 33, "lines_coords": [[[940.0, 507.0], [973.0, 507.0], [973.0, 701.0], [940.0, 701.0]], [[893.0, 509.0], [926.0, 509.0], [926.0, 673.0], [893.0, 673.0]]], "lines": ["大丈夫ですか", "千夏ちゃん"]}, {"box": [209, 542, 284, 642], "vertical": true, "font_size": 38, "lines_coords": [[[242.0, 542.0], [284.0, 542.0], [284.0, 615.0], [242.0, 615.0]], [[209.0, 545.0], [243.0, 545.0], [243.0, 642.0], [209.0, 642.0]]], "lines": ["うん", "なれた"]}, {"box": [948, 851, 993, 1156], "vertical": true, "font_size": 26, "lines_coords": [[[951.0, 851.0], [977.0, 851.0], [977.0, 1156.0], [951.0, 1156.0]]], "lines": ["ここで仕事するの？"]}, {"box": [537, 853, 651, 1056], "vertical": true, "font_size": 29, "lines_coords": [[[624.0, 853.0], [651.0, 853.0], [651.0, 1039.0], [624.0, 1039.0]], [[581.0, 853.0], [609.0, 853.0], [609.0, 970.0], [581.0, 970.0]], [[537.0, 853.0], [568.0, 853.0], [568.0, 1056.0], [537.0, 1056.0]]], "lines": ["ううん、ここは", "仕事場に", "行くための通路"]}, {"box": [434, 820, 454, 887], "vertical": true, "font_size": 17, "lines_coords": [[[437.0, 820.0], [454.0, 820.0], [451.0, 887.0], [434.0, 887.0]]], "lines": ["．．．"]}, {"box": [412, 832, 429, 915], "vertical": true, "font_size": 17, "lines_coords": [[[412.0, 832.0], [429.0, 832.0], [429.0, 915.0], [412.0, 915.0]]], "lines": ["それでも、これまでは"]}, {"box": [295, 834, 321, 1073], "vertical": true, "font_size": 22, "lines_coords": [[[296.0, 834.0], [318.0, 834.0], [318.0, 1068.0], [296.0, 1068.0]]], "lines": ["じゅうへいこう．．．？"]}, {"box": [367, 1284, 477, 1453], "vertical": true, "font_size": 31, "lines_coords": [[[445.0, 1284.0], [477.0, 1284.0], [477.0, 1400.0], [445.0, 1400.0]], [[406.0, 1284.0], [438.0, 1284.0], [438.0, 1453.0], [406.0, 1453.0]], [[367.0, 1287.0], [395.0, 1287.0], [395.0, 1421.0], [367.0, 1421.0]]], "lines": ["ここから", "重並行域って", "所に行くの"]}, {"box": [44, 1245, 162, 1451], "vertical": true, "font_size": 31, "lines_coords": [[[117.0, 1245.0], [154.0, 1245.0], [154.0, 1451.0], [117.0, 1451.0]], [[76.0, 1246.0], [110.0, 1245.0], [114.0, 1331.0], [79.0, 1332.0]], [[46.0, 1250.0], [68.0, 1250.0], [68.0, 1406.0], [46.0, 1406.0]]], "lines": ["時々他の世界と", "重なる", "場所のことよ"]}]}