{"version": "0.1.8", "img_width": 1362, "img_height": 1920, "blocks": [{"box": [69, 99, 1240, 414], "vertical": false, "font_size": 59, "lines_coords": [[[80.0, 107.0], [1170.0, 109.0], [1170.0, 171.0], [80.0, 170.0]], [[76.0, 176.0], [1238.0, 176.0], [1238.0, 248.0], [76.0, 248.0]], [[76.0, 253.0], [1240.0, 251.0], [1240.0, 320.0], [76.0, 321.0]], [[82.0, 332.0], [1044.0, 332.0], [1044.0, 387.0], [82.0, 387.0]]], "lines": ["ｄｅｆｉｎｉｔｅｌｙｔｏｏｋｆｉｍｅ．ｆｏｒｍｅｔｏａｄｉｌｓｔｒｏ", "えー．．．！？？？～～～！？ｏｔｈｏｖｉｎｇｈｅｎ．Ｂｕｔわかりましたが、１００Ｗ－Ｗｅｖｅｒｉｎｔｒｏｔｕｃｅｄ", "ｏｕｒｆｉｒｓｔｆｗｏｏｎｏｎｄｔｐｐｏｒｅｉｄｗｏｒｄｓ．ｃｎｄｙｏｕ．", "ｃａｎｂｅｔｔｈｅｒｅｗｉｌｂｅ「ｍｏｒｅｔｏｃｏｍｅ！"]}, {"box": [78, 478, 1187, 686], "vertical": false, "font_size": 60.666666666666664, "lines_coords": [[[84.0, 478.0], [1080.0, 478.0], [1080.0, 540.0], [84.0, 540.0]], [[78.0, 551.0], [1187.0, 551.0], [1187.0, 613.0], [78.0, 613.0]], [[86.0, 624.0], [769.0, 628.0], [769.0, 686.0], [86.0, 682.0]]], "lines": ["Ｗｅｌ，工ｄｂｅｔｔｅｒｇｅｔｂｏｃｋｔｏｗｏｒｋｏｎ．", "Ｂｏｏｋ４．Ｓｅｅｙｏｕｒｅｒをｑｇｉｎ＇ｗｈｅｎｉｔｓｏｕｔ．．．", "Ｔｒａｎｋｓａｇａｉｎｆｏｒｒｅａｄｒａｌ"]}]}