{"version": "0.1.8", "img_width": 1070, "img_height": 1600, "blocks": [{"box": [903, 175, 1013, 384], "vertical": true, "font_size": 27, "lines_coords": [[[982.0, 175.0], [1013.0, 175.0], [1013.0, 384.0], [982.0, 384.0]], [[943.0, 176.0], [970.0, 176.0], [970.0, 317.0], [943.0, 317.0]], [[904.0, 179.0], [926.0, 179.0], [926.0, 367.0], [904.0, 367.0]]], "lines": ["じゃとりあえず", "担当料理を", "決めましょうか"]}, {"box": [526, 170, 590, 336], "vertical": true, "font_size": 26, "lines_coords": [[[554.0, 170.0], [585.0, 170.0], [590.0, 335.0], [559.0, 335.0]], [[527.0, 176.0], [549.0, 176.0], [549.0, 335.0], [527.0, 335.0]]], "lines": ["あみだくじで", "いいですか？"]}, {"box": [279, 165, 321, 235], "vertical": true, "font_size": 42, "lines_coords": [[[279.0, 165.0], [321.0, 165.0], [321.0, 235.0], [279.0, 235.0]]], "lines": ["おう"]}, {"box": [81, 275, 106, 400], "vertical": true, "font_size": 22, "lines_coords": [[[81.0, 276.0], [103.0, 276.0], [103.0, 400.0], [81.0, 400.0]]], "lines": ["あまじ？"]}, {"box": [969, 634, 996, 676], "vertical": true, "font_size": 27, "lines_coords": [[[969.0, 634.0], [996.0, 634.0], [996.0, 676.0], [969.0, 676.0]]], "lines": ["？"]}, {"box": [598, 609, 626, 723], "vertical": true, "font_size": 28, "lines_coords": [[[598.0, 610.0], [626.0, 610.0], [626.0, 721.0], [598.0, 721.0]]], "lines": ["あいやー"]}, {"box": [60, 607, 265, 784], "vertical": true, "font_size": 27, "lines_coords": [[[243.0, 612.0], [265.0, 612.0], [265.0, 784.0], [243.0, 784.0]], [[203.0, 610.0], [229.0, 610.0], [229.0, 759.0], [203.0, 759.0]], [[170.0, 607.0], [204.0, 607.0], [204.0, 690.0], [170.0, 690.0]], [[120.0, 610.0], [146.0, 610.0], [146.0, 737.0], [120.0, 737.0]], [[92.0, 612.0], [114.0, 612.0], [114.0, 735.0], [92.0, 735.0]], [[60.0, 612.0], [82.0, 612.0], [82.0, 759.0], [60.0, 759.0]]], "lines": ["あたしあんまし", "料理得意じゃ", "なくて", "多分焦がし", "ちゃったり", "するからさぁ"]}, {"box": [946, 1093, 1002, 1245], "vertical": true, "font_size": 28, "lines_coords": [[[976.0, 1093.0], [1002.0, 1093.0], [1002.0, 1245.0], [976.0, 1245.0]], [[946.0, 1093.0], [968.0, 1093.0], [968.0, 1220.0], [946.0, 1220.0]]], "lines": ["大丈夫ですよ", "なおさん！"]}, {"box": [59, 865, 189, 993], "vertical": true, "font_size": 27, "lines_coords": [[[156.0, 865.0], [189.0, 865.0], [189.0, 968.0], [156.0, 968.0]], [[128.0, 867.0], [156.0, 867.0], [156.0, 968.0], [128.0, 968.0]], [[93.0, 867.0], [121.0, 867.0], [124.0, 993.0], [96.0, 993.0]], [[59.0, 865.0], [87.0, 865.0], [87.0, 968.0], [59.0, 968.0]]], "lines": ["焦げない", "サラダが", "いいなーと", "思って．．"]}, {"box": [937, 1309, 998, 1515], "vertical": true, "font_size": 28, "lines_coords": [[[971.0, 1309.0], [998.0, 1309.0], [998.0, 1471.0], [971.0, 1471.0]], [[940.0, 1310.0], [962.0, 1310.0], [959.0, 1515.0], [937.0, 1515.0]]], "lines": ["そんなに難しい", "料理じゃないですよ"]}, {"box": [821, 1426, 887, 1521], "vertical": true, "font_size": 28, "lines_coords": [[[846.0, 1426.0], [887.0, 1426.0], [887.0, 1503.0], [846.0, 1503.0]], [[821.0, 1426.0], [854.0, 1426.0], [854.0, 1521.0], [821.0, 1521.0]]], "lines": ["一緒に", "がんばり"]}, {"box": [799, 1428, 821, 1518], "vertical": true, "font_size": 22, "lines_coords": [[[799.0, 1428.0], [821.0, 1428.0], [821.0, 1518.0], [799.0, 1518.0]]], "lines": ["ましょ！"]}, {"box": [290, 1241, 318, 1365], "vertical": true, "font_size": 27, "lines_coords": [[[290.0, 1243.0], [317.0, 1243.0], [317.0, 1362.0], [290.0, 1362.0]]], "lines": ["ううーん"]}]}