{"version": "0.1.8", "img_width": 1070, "img_height": 1600, "blocks": [{"box": [896, 71, 986, 467], "vertical": true, "font_size": 34, "lines_coords": [[[938.0, 71.0], [976.0, 71.0], [976.0, 350.0], [938.0, 350.0]], [[896.0, 73.0], [927.0, 73.0], [927.0, 467.0], [896.0, 467.0]]], "lines": ["犬養は真琴と一緒で", "私が担当してる魔女なんだよ"]}, {"box": [174, 65, 238, 315], "vertical": true, "font_size": 28, "lines_coords": [[[204.0, 65.0], [238.0, 65.0], [238.0, 129.0], [204.0, 129.0]], [[176.0, 71.0], [198.0, 71.0], [198.0, 315.0], [176.0, 315.0]]], "lines": ["え！", "そうだったんですか"]}, {"box": [902, 587, 999, 764], "vertical": true, "font_size": 25, "lines_coords": [[[968.0, 589.0], [995.0, 589.0], [995.0, 740.0], [968.0, 740.0]], [[930.0, 587.0], [957.0, 587.0], [957.0, 764.0], [930.0, 764.0]], [[902.0, 590.0], [923.0, 590.0], [923.0, 739.0], [902.0, 739.0]]], "lines": ["あの子はねー", "美人だし実力も", "あるんだけど"]}, {"box": [546, 585, 603, 767], "vertical": true, "font_size": 24, "lines_coords": [[[576.0, 585.0], [602.0, 585.0], [602.0, 765.0], [576.0, 765.0]], [[546.0, 587.0], [568.0, 587.0], [568.0, 740.0], [546.0, 740.0]]], "lines": ["いまいちツイて", "ないんだよね"]}, {"box": [248, 595, 279, 785], "vertical": true, "font_size": 26, "lines_coords": [[[248.0, 595.0], [274.0, 595.0], [274.0, 785.0], [248.0, 785.0]]], "lines": ["そうなんですか"]}, {"box": [891, 1004, 995, 1250], "vertical": true, "font_size": 29, "lines_coords": [[[960.0, 1004.0], [991.0, 1004.0], [995.0, 1171.0], [963.0, 1171.0]], [[920.0, 1004.0], [951.0, 1004.0], [951.0, 1200.0], [920.0, 1200.0]], [[891.0, 1007.0], [913.0, 1007.0], [913.0, 1250.0], [891.0, 1250.0]]], "lines": ["なるほどねー", "真琴は魔術系は", "まだまだってとこが"]}, {"box": [142, 1001, 338, 1252], "vertical": true, "font_size": 30, "lines_coords": [[[296.0, 1006.0], [329.0, 1006.0], [329.0, 1187.0], [296.0, 1187.0]], [[257.0, 1006.0], [284.0, 1006.0], [284.0, 1251.0], [257.0, 1251.0]], [[210.0, 1001.0], [243.0, 1001.0], [246.0, 1201.0], [214.0, 1201.0]], [[173.0, 1003.0], [204.0, 1003.0], [204.0, 1173.0], [173.0, 1173.0]], [[142.0, 1006.0], [168.0, 1006.0], [168.0, 1143.0], [142.0, 1143.0]]], "lines": ["はいお世話に", "なってるお父さんが", "農家さんなので", "すごく勉強に", "なってます"]}, {"box": [874, 1315, 979, 1540], "vertical": true, "font_size": 29, "lines_coords": [[[948.0, 1315.0], [979.0, 1315.0], [976.0, 1529.0], [945.0, 1529.0]], [[905.0, 1315.0], [938.0, 1315.0], [938.0, 1540.0], [905.0, 1540.0]], [[874.0, 1318.0], [901.0, 1318.0], [901.0, 1451.0], [874.0, 1451.0]]], "lines": ["でも植物の知識は", "大分身につけてる", "みたいだね"]}, {"box": [149, 1371, 221, 1462], "vertical": true, "font_size": 40, "lines_coords": [[[182.0, 1371.0], [221.0, 1371.0], [221.0, 1462.0], [182.0, 1462.0]], [[149.0, 1371.0], [189.0, 1371.0], [189.0, 1460.0], [149.0, 1460.0]]], "lines": ["そっか", "そっか"]}]}