{"version": "0.1.8", "img_width": 1070, "img_height": 1600, "blocks": [{"box": [423, 1346, 663, 1415], "vertical": false, "font_size": 66, "lines_coords": [[[423.0, 1346.0], [663.0, 1350.0], [663.0, 1415.0], [423.0, 1412.0]]], "lines": ["ふらいんぐ"]}, {"box": [526, 1453, 773, 1473], "vertical": false, "font_size": 20, "lines_coords": [[[526.0, 1453.0], [773.0, 1453.0], [773.0, 1473.0], [526.0, 1473.0]]], "lines": ["そしてそれを、Ｗｉｔｃｈを"]}, {"box": [698, 1364, 877, 1414], "vertical": false, "font_size": 44, "lines_coords": [[[699.0, 1364.0], [877.0, 1370.0], [876.0, 1414.0], [698.0, 1407.0]]], "lines": ["「ういつ"]}]}