{"version": "0.1.8", "img_width": 1070, "img_height": 1600, "blocks": [{"box": [810, 152, 856, 200], "vertical": false, "font_size": 44, "lines_coords": [[[810.0, 156.0], [856.0, 156.0], [856.0, 200.0], [810.0, 200.0]]], "lines": ["ん"]}, {"box": [660, 150, 742, 315], "vertical": true, "font_size": 30, "lines_coords": [[[699.0, 150.0], [731.0, 150.0], [731.0, 315.0], [699.0, 315.0]], [[660.0, 150.0], [688.0, 150.0], [688.0, 260.0], [660.0, 260.0]]], "lines": ["今度はチトが", "狙ってら"]}, {"box": [646, 707, 949, 739], "vertical": false, "font_size": 32, "lines_coords": [[[646.0, 707.0], [949.0, 707.0], [949.0, 739.0], [646.0, 739.0]]], "lines": ["ダウダヴダダタダダダツ"]}, {"box": [441, 365, 532, 490], "vertical": true, "font_size": 36, "lines_coords": [[[482.0, 365.0], [521.0, 365.0], [521.0, 464.0], [482.0, 464.0]], [[442.0, 368.0], [474.0, 368.0], [474.0, 490.0], [442.0, 490.0]]], "lines": ["本当だ", "頑張れー"]}, {"box": [96, 704, 378, 735], "vertical": false, "font_size": 26, "lines_coords": [[[96.0, 704.0], [378.0, 709.0], [378.0, 735.0], [96.0, 731.0]]], "lines": ["かかかわからなかった"]}, {"box": [604, 1076, 684, 1312], "vertical": true, "font_size": 35, "lines_coords": [[[642.0, 1078.0], [679.0, 1076.0], [684.0, 1242.0], [646.0, 1243.0]], [[604.0, 1081.0], [637.0, 1081.0], [637.0, 1312.0], [604.0, 1312.0]]], "lines": ["あはははっ", "チトさんったら"]}, {"box": [187, 1132, 322, 1376], "vertical": true, "font_size": 33, "lines_coords": [[[274.0, 1132.0], [309.0, 1132.0], [306.0, 1376.0], [271.0, 1376.0]], [[231.0, 1135.0], [263.0, 1135.0], [263.0, 1307.0], [231.0, 1307.0]], [[187.0, 1135.0], [220.0, 1135.0], [220.0, 1310.0], [187.0, 1310.0]]], "lines": ["行ったり来たり", "しちゃって", "まずよー！"]}]}