{"version": "0.1.8", "img_width": 1070, "img_height": 1600, "blocks": [{"box": [246, 164, 296, 242], "vertical": true, "font_size": 44, "lines_coords": [[[246.0, 164.0], [296.0, 164.0], [296.0, 242.0], [246.0, 242.0]]], "lines": ["あい"]}, {"box": [174, 239, 212, 376], "vertical": true, "font_size": 44, "lines_coords": [[[174.0, 239.0], [212.0, 239.0], [212.0, 376.0], [174.0, 376.0]]], "lines": ["いくよー"]}, {"box": [632, 495, 771, 615], "vertical": true, "font_size": 38, "lines_coords": [[[727.0, 495.0], [771.0, 495.0], [771.0, 560.0], [727.0, 560.0]], [[632.0, 526.0], [671.0, 526.0], [671.0, 615.0], [632.0, 615.0]]], "lines": ["いち", "にーの"]}, {"box": [676, 648, 706, 710], "vertical": true, "font_size": 38, "lines_coords": [[[676.0, 648.0], [706.0, 648.0], [706.0, 710.0], [676.0, 710.0]]], "lines": ["さん"]}, {"box": [373, 496, 430, 660], "vertical": true, "font_size": 23, "lines_coords": [[[404.0, 496.0], [426.0, 496.0], [426.0, 610.0], [404.0, 610.0]], [[374.0, 496.0], [398.0, 496.0], [396.0, 659.0], [373.0, 659.0]]], "lines": ["ありがとう", "ございましたー"]}, {"box": [306, 837, 335, 958], "vertical": true, "font_size": 26, "lines_coords": [[[306.0, 837.0], [332.0, 837.0], [332.0, 957.0], [306.0, 957.0]]], "lines": ["どれどれ"]}, {"box": [516, 1168, 541, 1252], "vertical": true, "font_size": 25, "lines_coords": [[[516.0, 1168.0], [541.0, 1168.0], [541.0, 1252.0], [516.0, 1252.0]]], "lines": ["．．．．．．"]}, {"box": [89, 1262, 162, 1389], "vertical": true, "font_size": 57, "lines_coords": [[[106.0, 1262.0], [162.0, 1271.0], [145.0, 1389.0], [89.0, 1379.0]]], "lines": ["城が．．．"]}]}