{"version": "0.1.8", "img_width": 1070, "img_height": 1600, "blocks": [{"box": [495, 146, 534, 239], "vertical": true, "font_size": 39, "lines_coords": [[[495.0, 146.0], [534.0, 146.0], [534.0, 239.0], [495.0, 239.0]]], "lines": ["うんっ"]}, {"box": [321, 164, 352, 284], "vertical": true, "font_size": 28, "lines_coords": [[[321.0, 165.0], [349.0, 165.0], [349.0, 284.0], [321.0, 284.0]]], "lines": ["そうする"]}, {"box": [877, 607, 948, 820], "vertical": true, "font_size": 30, "lines_coords": [[[915.0, 607.0], [948.0, 607.0], [948.0, 703.0], [915.0, 703.0]], [[879.0, 609.0], [907.0, 609.0], [905.0, 818.0], [877.0, 818.0]]], "lines": ["じゃあ", "こうしようかな"]}, {"box": [154, 373, 193, 478], "vertical": true, "font_size": 39, "lines_coords": [[[154.0, 373.0], [193.0, 373.0], [193.0, 478.0], [154.0, 478.0]]], "lines": ["よしっ"]}, {"box": [843, 1015, 937, 1228], "vertical": true, "font_size": 40, "lines_coords": [[[898.0, 1018.0], [937.0, 1018.0], [937.0, 1159.0], [898.0, 1159.0]], [[843.0, 1015.0], [885.0, 1015.0], [885.0, 1228.0], [843.0, 1228.0]]], "lines": ["それまで", "千夏ちゃんを"]}, {"box": [204, 1021, 308, 1235], "vertical": true, "font_size": 40, "lines_coords": [[[251.0, 1021.0], [293.0, 1021.0], [296.0, 1235.0], [254.0, 1235.0]], [[204.0, 1023.0], [242.0, 1023.0], [242.0, 1232.0], [204.0, 1232.0]]], "lines": ["魔女見習いに", "任命しまーす"]}]}