{"version": "0.1.8", "img_width": 764, "img_height": 1200, "blocks": [{"box": [617, 91, 734, 292], "vertical": true, "font_size": 24, "lines_coords": [[[710.0, 91.0], [734.0, 91.0], [734.0, 183.0], [710.0, 183.0]], [[674.0, 91.0], [703.0, 91.0], [703.0, 292.0], [674.0, 292.0]], [[643.0, 91.0], [667.0, 91.0], [665.0, 292.0], [640.0, 292.0]], [[617.0, 91.0], [637.0, 91.0], [637.0, 256.0], [617.0, 256.0]]], "lines": ["そこでは", "本当に強くなりたい", "やつらだけが決闘に", "あけくれている。"]}, {"box": [123, 221, 215, 360], "vertical": true, "font_size": 25, "lines_coords": [[[176.0, 221.0], [206.0, 221.0], [206.0, 294.0], [176.0, 294.0]], [[148.0, 223.0], [172.0, 223.0], [172.0, 360.0], [148.0, 360.0]], [[123.0, 223.0], [144.0, 223.0], [144.0, 323.0], [123.0, 323.0]]], "lines": ["黒城も", "そこの出身者", "らしいよ。"]}, {"box": [600, 391, 643, 452], "vertical": true, "font_size": 31, "lines_coords": [[[612.0, 391.0], [643.0, 391.0], [643.0, 452.0], [612.0, 452.0]]], "lines": ["やつも"]}, {"box": [545, 516, 687, 627], "vertical": true, "font_size": 20, "lines_coords": [[[662.0, 516.0], [687.0, 516.0], [687.0, 583.0], [662.0, 583.0]], [[642.0, 517.0], [662.0, 517.0], [662.0, 592.0], [642.0, 592.0]], [[619.0, 519.0], [636.0, 519.0], [636.0, 626.0], [619.0, 626.0]], [[590.0, 516.0], [610.0, 516.0], [610.0, 609.0], [590.0, 609.0]], [[567.0, 517.0], [587.0, 517.0], [587.0, 591.0], [567.0, 591.0]], [[546.0, 519.0], [562.0, 519.0], [562.0, 615.0], [546.0, 615.0]]], "lines": ["だから、", "そこには", "とんでもなく", "強いやつが", "わんさか", "いるんだよ"]}, {"box": [187, 530, 308, 612], "vertical": true, "font_size": 24, "lines_coords": [[[282.0, 530.0], [308.0, 530.0], [308.0, 597.0], [282.0, 597.0]], [[257.0, 532.0], [283.0, 532.0], [283.0, 608.0], [257.0, 608.0]], [[230.0, 532.0], [256.0, 532.0], [256.0, 592.0], [230.0, 592.0]], [[207.0, 530.0], [236.0, 530.0], [236.0, 609.0], [207.0, 609.0]], [[187.0, 532.0], [207.0, 532.0], [207.0, 612.0], [187.0, 612.0]]], "lines": ["きっと、", "くやしい", "目にも", "いっぱい", "あうけど、"]}, {"box": [76, 532, 124, 625], "vertical": true, "font_size": 24, "lines_coords": [[[104.0, 532.0], [124.0, 532.0], [124.0, 607.0], [104.0, 607.0]], [[76.0, 532.0], [96.0, 532.0], [96.0, 625.0], [76.0, 625.0]]], "lines": ["それでも", "行くかい？"]}, {"box": [677, 711, 752, 919], "vertical": true, "font_size": 31, "lines_coords": [[[719.0, 712.0], [752.0, 712.0], [747.0, 919.0], [714.0, 919.0]], [[677.0, 711.0], [706.0, 711.0], [706.0, 832.0], [677.0, 832.0]]], "lines": ["ったりめーだ！！", "行くぜ！！"]}, {"box": [263, 708, 319, 953], "vertical": true, "font_size": 24, "lines_coords": [[[291.0, 710.0], [316.0, 710.0], [316.0, 866.0], [291.0, 866.0]], [[263.0, 710.0], [287.0, 710.0], [287.0, 952.0], [263.0, 952.0]]], "lines": ["強くなれるなら", "なんだってやってヤる！！！"]}]}