{"version": "0.1.8", "img_width": 764, "img_height": 1200, "blocks": [{"box": [685, 52, 748, 266], "vertical": true, "font_size": 30, "lines_coords": [[[711.0, 53.0], [746.0, 52.0], [748.0, 123.0], [713.0, 124.0]], [[685.0, 57.0], [710.0, 57.0], [711.0, 266.0], [686.0, 266.0]]], "lines": ["さぁ、", "どんどんいくぞ！！"]}, {"box": [394, 546, 497, 605], "vertical": false, "font_size": 24, "lines_coords": [[[394.0, 546.0], [494.0, 546.0], [494.0, 575.0], [394.0, 575.0]], [[396.0, 566.0], [461.0, 566.0], [461.0, 590.0], [396.0, 590.0]], [[398.0, 585.0], [482.0, 585.0], [482.0, 605.0], [398.0, 605.0]]], "lines": ["筋肉スリヴァー", "バワー", "タフネス"]}, {"box": [49, 444, 198, 503], "vertical": false, "font_size": 20, "lines_coords": [[[49.0, 447.0], [146.0, 447.0], [146.0, 467.0], [49.0, 467.0]], [[49.0, 467.0], [196.0, 465.0], [196.0, 485.0], [49.0, 487.0]], [[50.0, 483.0], [196.0, 480.0], [196.0, 500.0], [50.0, 503.0]]], "lines": ["針刺スリヴァー", "バワー３（２＋）", "タフネス，３（２＋））"]}, {"box": [76, 603, 209, 787], "vertical": true, "font_size": 28, "lines_coords": [[[172.0, 603.0], [209.0, 603.0], [209.0, 698.0], [172.0, 698.0]], [[145.0, 605.0], [171.0, 605.0], [168.0, 737.0], [142.0, 737.0]], [[110.0, 604.0], [134.0, 604.0], [134.0, 759.0], [110.0, 759.0]], [[77.0, 604.0], [101.0, 604.0], [101.0, 787.0], [77.0, 787.0]]], "lines": ["くくく、", "きやがれ！！", "おまえなんか", "こわくないぜ！！"]}, {"box": [624, 857, 707, 975], "vertical": true, "font_size": 23, "lines_coords": [[[680.0, 858.0], [703.0, 858.0], [704.0, 958.0], [681.0, 958.0]], [[650.0, 857.0], [674.0, 857.0], [678.0, 975.0], [653.0, 975.0]], [[624.0, 858.0], [645.0, 858.0], [647.0, 956.0], [626.0, 956.0]]], "lines": ["勝ちゃんが、", "すごい勢いで", "押してる！！"]}, {"box": [285, 858, 336, 1027], "vertical": true, "font_size": 22, "lines_coords": [[[310.0, 858.0], [333.0, 858.0], [336.0, 991.0], [312.0, 991.0]], [[285.0, 858.0], [305.0, 858.0], [307.0, 1027.0], [287.0, 1027.0]]], "lines": ["あいつはなんで", "手を出さないんだ！？"]}, {"box": [394, 1074, 419, 1143], "vertical": true, "font_size": 25, "lines_coords": [[[394.0, 1074.0], [419.0, 1074.0], [419.0, 1143.0], [394.0, 1143.0]]], "lines": ["だけど、"]}, {"box": [188, 1003, 214, 1030], "vertical": false, "font_size": 27, "lines_coords": [[[188.0, 1003.0], [214.0, 1003.0], [214.0, 1030.0], [188.0, 1030.0]]], "lines": ["ゼイ"]}, {"box": [217, 1066, 239, 1099], "vertical": true, "font_size": 22, "lines_coords": [[[217.0, 1066.0], [239.0, 1066.0], [239.0, 1099.0], [217.0, 1099.0]]], "lines": ["ゼイ"]}, {"box": [64, 849, 98, 1037], "vertical": true, "font_size": 24, "lines_coords": [[[64.0, 849.0], [89.0, 849.0], [93.0, 1037.0], [69.0, 1037.0]]], "lines": ["なんか変だよ．．．。"]}]}